MANIFEST.in
setup.py
easy_lang_GUI/ChooseLang.py
easy_lang_GUI/__init__.py
easy_lang_GUI.egg-info/PKG-INFO
easy_lang_GUI.egg-info/SOURCES.txt
easy_lang_GUI.egg-info/dependency_links.txt
easy_lang_GUI.egg-info/requires.txt
easy_lang_GUI.egg-info/top_level.txt
easy_lang_GUI/icos/langchoosing.png