Metadata-Version: 1.0
Name: easy-lang-GUI
Version: 0.1.12
Summary: GUI addon for easy_languages.
Home-page: UNKNOWN
Author: Larty
Author-email: UNKNOWN
License: UNKNOWN
Platform: UNKNOWN
